riemann_client/__init__.py
riemann_client/__main__.py
riemann_client/client.py
riemann_client/command.py
riemann_client/riemann_pb2.py
riemann_client/riemann_py2_pb2.py
riemann_client/riemann_py3_pb2.py
riemann_client/transport.py
riemann_client-7.0.0.dist-info/LICENSE
riemann_client-7.0.0.dist-info/METADATA
riemann_client-7.0.0.dist-info/WHEEL
riemann_client-7.0.0.dist-info/entry_points.txt
riemann_client-7.0.0.dist-info/top_level.txt
riemann_client-7.0.0.dist-info/RECORD
