Metadata-Version: 2.1
Name: riemann-client
Version: 7.0.0
Summary: A Riemann client and command line tool
Home-page: https://github.com/borntyping/python-riemann-client
Author: Sam Clements
Author-email: sam.clements@datasift.com
License: MIT
Classifier: Development Status :: 7 - Inactive
Classifier: License :: OSI Approved
Classifier: License :: OSI Approved :: MIT License
Classifier: Programming Language :: Python
Classifier: Programming Language :: Python :: 2
Classifier: Programming Language :: Python :: 2.6
Classifier: Programming Language :: Python :: 2.7
Classifier: Programming Language :: Python :: 3
Classifier: Programming Language :: Python :: 3.4
Classifier: Programming Language :: Python :: 3.5
Classifier: Topic :: Software Development :: Libraries
Classifier: Topic :: System :: Monitoring
Classifier: Topic :: System :: Networking
Classifier: Topic :: System :: Systems Administration
License-File: LICENSE
Requires-Dist: click>=3.1
Requires-Dist: protobuf<4.0.0,>=3.2.0
Provides-Extra: docs
Requires-Dist: sphinx; extra == "docs"
Requires-Dist: sphinx_rtd_theme; extra == "docs"
